{
    "current_scene": "gameplay",
    "current_program_scene": "gameplay",
    "scene_order": [
        {
            "name": "gameplay"
        },
        {
            "name": "mappool"
        }
    ],
    "name": "USC2026",
    "groups": [
        {
            "prev_ver": 536870916,
            "name": "osu_clients",
            "uuid": "91e24224-4a94-477c-9511-f8bed15ac9e7",
            "id": "group",
            "versioned_id": "group",
            "settings": {
                "id_counter": 0,
                "custom_size": true,
                "cx": 1920,
                "cy": 720,
                "items": [
                    {
                        "name": "osu_0",
                        "source_uuid": "d9a304d4-76f8-443b-b337-c078c9e2496c",
                        "visible": true,
                        "locked": true,
                        "rot": 0.0,
                        "scale_ref": {
                            "x": 1920.0,
                            "y": 1080.0
                        },
                        "align": 5,
                        "bounds_type": 0,
                        "bounds_align": 0,
                        "bounds_crop": false,
                        "crop_left": 0,
                        "crop_top": 0,
                        "crop_right": 0,
                        "crop_bottom": 0,
                        "id": 3,
                        "group_item_backup": false,
                        "pos": {
                            "x": 240.0,
                            "y": 0.0
                        },
                        "pos_rel": {
                            "x": -1.3333333730697632,
                            "y": -1.0
                        },
                        "scale": {
                            "x": 1.0,
                            "y": 1.0
                        },
                        "scale_rel": {
                            "x": 1.0,
                            "y": 1.0
                        },
                        "bounds": {
                            "x": 0.0,
                            "y": 0.0
                        },
                        "bounds_rel": {
                            "x": 0.0,
                            "y": 0.0
                        },
                        "scale_filter": "disable",
                        "blend_method": "default",
                        "blend_type": "normal",
                        "show_transition": {
                            "duration": 0
                        },
                        "hide_transition": {
                            "duration": 0
                        },
                        "private_settings": {}
                    },
                    {
                        "name": "osu_1",
                        "source_uuid": "f1c4fdcf-52ee-450c-9054-b2edd7a7861f",
                        "visible": true,
                        "locked": true,
                        "rot": 0.0,
                        "scale_ref": {
                            "x": 1920.0,
                            "y": 1080.0
                        },
                        "align": 5,
                        "bounds_type": 0,
                        "bounds_align": 0,
                        "bounds_crop": false,
                        "crop_left": 0,
                        "crop_top": 0,
                        "crop_right": 0,
                        "crop_bottom": 0,
                        "id": 4,
                        "group_item_backup": false,
                        "pos": {
                            "x": 0.0,
                            "y": 360.0
                        },
                        "pos_rel": {
                            "x": -1.7777777910232544,
                            "y": -0.3333333134651184
                        },
                        "scale": {
                            "x": 1.0,
                            "y": 1.0
                        },
                        "scale_rel": {
                            "x": 1.0,
                            "y": 1.0
                        },
                        "bounds": {
                            "x": 0.0,
                            "y": 0.0
                        },
                        "bounds_rel": {
                            "x": 0.0,
                            "y": 0.0
                        },
                        "scale_filter": "disable",
                        "blend_method": "default",
                        "blend_type": "normal",
                        "show_transition": {
                            "duration": 0
                        },
                        "hide_transition": {
                            "duration": 0
                        },
                        "private_settings": {}
                    },
                    {
                        "name": "osu_2",
                        "source_uuid": "74814e97-60e8-4a64-a404-76626034266d",
                        "visible": true,
                        "locked": true,
                        "rot": 0.0,
                        "scale_ref": {
                            "x": 1920.0,
                            "y": 1080.0
                        },
                        "align": 5,
                        "bounds_type": 0,
                        "bounds_align": 0,
                        "bounds_crop": false,
                        "crop_left": 0,
                        "crop_top": 0,
                        "crop_right": 0,
                        "crop_bottom": 0,
                        "id": 5,
                        "group_item_backup": false,
                        "pos": {
                            "x": 480.0,
                            "y": 360.0
                        },
                        "pos_rel": {
                            "x": -0.8888888955116272,
                            "y": -0.3333333134651184
                        },
                        "scale": {
                            "x": 1.0,
                            "y": 1.0
                        },
                        "scale_rel": {
                            "x": 1.0,
                            "y": 1.0
                        },
                        "bounds": {
                            "x": 0.0,
                            "y": 0.0
                        },
                        "bounds_rel": {
                            "x": 0.0,
                            "y": 0.0
                        },
                        "scale_filter": "disable",
                        "blend_method": "default",
                        "blend_type": "normal",
                        "show_transition": {
                            "duration": 0
                        },
                        "hide_transition": {
                            "duration": 0
                        },
                        "private_settings": {}
                    },
                    {
                        "name": "osu_3",
                        "source_uuid": "4d7b2937-3850-468f-a270-c7175b8db295",
                        "visible": true,
                        "locked": true,
                        "rot": 0.0,
                        "scale_ref": {
                            "x": 1920.0,
                            "y": 1080.0
                        },
                        "align": 5,
                        "bounds_type": 0,
                        "bounds_align": 0,
                        "bounds_crop": false,
                        "crop_left": 0,
                        "crop_top": 0,
                        "crop_right": 0,
                        "crop_bottom": 0,
                        "id": 6,
                        "group_item_backup": false,
                        "pos": {
                            "x": 1199.0,
                            "y": 0.0
                        },
                        "pos_rel": {
                            "x": 0.442592591047287,
                            "y": -1.0
                        },
                        "scale": {
                            "x": 1.0,
                            "y": 1.0
                        },
                        "scale_rel": {
                            "x": 1.0,
                            "y": 1.0
                        },
                        "bounds": {
                            "x": 0.0,
                            "y": 0.0
                        },
                        "bounds_rel": {
                            "x": 0.0,
                            "y": 0.0
                        },
                        "scale_filter": "disable",
                        "blend_method": "default",
                        "blend_type": "normal",
                        "show_transition": {
                            "duration": 0
                        },
                        "hide_transition": {
                            "duration": 0
                        },
                        "private_settings": {}
                    },
                    {
                        "name": "osu_4",
                        "source_uuid": "4c171870-5a0e-4aa6-b13b-7949cc213cff",
                        "visible": true,
                        "locked": true,
                        "rot": 0.0,
                        "scale_ref": {
                            "x": 1920.0,
                            "y": 1080.0
                        },
                        "align": 5,
                        "bounds_type": 0,
                        "bounds_align": 0,
                        "bounds_crop": false,
                        "crop_left": 0,
                        "crop_top": 0,
                        "crop_right": 0,
                        "crop_bottom": 0,
                        "id": 7,
                        "group_item_backup": false,
                        "pos": {
                            "x": 960.0,
                            "y": 360.0
                        },
                        "pos_rel": {
                            "x": 0.0,
                            "y": -0.3333333134651184
                        },
                        "scale": {
                            "x": 1.0,
                            "y": 1.0
                        },
                        "scale_rel": {
                            "x": 1.0,
                            "y": 1.0
                        },
                        "bounds": {
                            "x": 0.0,
                            "y": 0.0
                        },
                        "bounds_rel": {
                            "x": 0.0,
                            "y": 0.0
                        },
                        "scale_filter": "disable",
                        "blend_method": "default",
                        "blend_type": "normal",
                        "show_transition": {
                            "duration": 0
                        },
                        "hide_transition": {
                            "duration": 0
                        },
                        "private_settings": {}
                    },
                    {
                        "name": "osu_5",
                        "source_uuid": "3b912092-2f46-458d-9c51-c18c91d7996a",
                        "visible": true,
                        "locked": true,
                        "rot": 0.0,
                        "scale_ref": {
                            "x": 1920.0,
                            "y": 1080.0
                        },
                        "align": 5,
                        "bounds_type": 0,
                        "bounds_align": 0,
                        "bounds_crop": false,
                        "crop_left": 0,
                        "crop_top": 0,
                        "crop_right": 0,
                        "crop_bottom": 0,
                        "id": 8,
                        "group_item_backup": false,
                        "pos": {
                            "x": 1440.0,
                            "y": 360.0
                        },
                        "pos_rel": {
                            "x": 0.8888888955116272,
                            "y": -0.3333333134651184
                        },
                        "scale": {
                            "x": 1.0,
                            "y": 1.0
                        },
                        "scale_rel": {
                            "x": 1.0,
                            "y": 1.0
                        },
                        "bounds": {
                            "x": 0.0,
                            "y": 0.0
                        },
                        "bounds_rel": {
                            "x": 0.0,
                            "y": 0.0
                        },
                        "scale_filter": "disable",
                        "blend_method": "default",
                        "blend_type": "normal",
                        "show_transition": {
                            "duration": 0
                        },
                        "hide_transition": {
                            "duration": 0
                        },
                        "private_settings": {}
                    }
                ]
            },
            "mixers": 0,
            "sync": 0,
            "flags": 0,
            "volume": 1.0,
            "balance": 0.5,
            "enabled": true,
            "muted": false,
            "push-to-mute": false,
            "push-to-mute-delay": 0,
            "push-to-talk": false,
            "push-to-talk-delay": 0,
            "hotkeys": {
                "libobs.show_scene_item.3": [],
                "libobs.hide_scene_item.3": [],
                "libobs.show_scene_item.4": [],
                "libobs.hide_scene_item.4": [],
                "libobs.show_scene_item.5": [],
                "libobs.hide_scene_item.5": [],
                "libobs.show_scene_item.6": [],
                "libobs.hide_scene_item.6": [],
                "libobs.show_scene_item.7": [],
                "libobs.hide_scene_item.7": [],
                "libobs.show_scene_item.8": [],
                "libobs.hide_scene_item.8": []
            },
            "deinterlace_mode": 0,
            "deinterlace_field_order": 0,
            "monitoring_type": 0,
            "canvas_uuid": "6c69626f-6273-4c00-9d88-c5136d61696e",
            "private_settings": {}
        },
        {
            "prev_ver": 536870916,
            "name": "names",
            "uuid": "39f30a38-2a54-4b57-8416-a30346ccaa47",
            "id": "group",
            "versioned_id": "group",
            "settings": {
                "id_counter": 0,
                "custom_size": true,
                "cx": 1920,
                "cy": 400,
                "items": [
                    {
                        "name": "name_1",
                        "source_uuid": "9ebf5713-15e7-4168-9571-5e563578ada7",
                        "visible": true,
                        "locked": true,
                        "rot": 0.0,
                        "scale_ref": {
                            "x": 1920.0,
                            "y": 1080.0
                        },
                        "align": 5,
                        "bounds_type": 0,
                        "bounds_align": 0,
                        "bounds_crop": false,
                        "crop_left": 0,
                        "crop_top": 0,
                        "crop_right": 0,
                        "crop_bottom": 0,
                        "id": 13,
                        "group_item_backup": false,
                        "pos": {
                            "x": 240.0,
                            "y": 0.0
                        },
                        "pos_rel": {
                            "x": -1.3333333730697632,
                            "y": -1.0
                        },
                        "scale": {
                            "x": 1.0,
                            "y": 1.0
                        },
                        "scale_rel": {
                            "x": 1.0,
                            "y": 1.0
                        },
                        "bounds": {
                            "x": 0.0,
                            "y": 0.0
                        },
                        "bounds_rel": {
                            "x": 0.0,
                            "y": 0.0
                        },
                        "scale_filter": "disable",
                        "blend_method": "default",
                        "blend_type": "normal",
                        "show_transition": {
                            "duration": 0
                        },
                        "hide_transition": {
                            "duration": 0
                        },
                        "private_settings": {}
                    },
                    {
                        "name": "name_2",
                        "source_uuid": "c6b60609-e4d0-45ac-bdfb-3aca589e4be4",
                        "visible": true,
                        "locked": true,
                        "rot": 0.0,
                        "scale_ref": {
                            "x": 1920.0,
                            "y": 1080.0
                        },
                        "align": 5,
                        "bounds_type": 0,
                        "bounds_align": 0,
                        "bounds_crop": false,
                        "crop_left": 0,
                        "crop_top": 0,
                        "crop_right": 0,
                        "crop_bottom": 0,
                        "id": 14,
                        "group_item_backup": false,
                        "pos": {
                            "x": 0.0,
                            "y": 360.0
                        },
                        "pos_rel": {
                            "x": -1.7777777910232544,
                            "y": -0.3333333730697632
                        },
                        "scale": {
                            "x": 1.0,
                            "y": 1.0
                        },
                        "scale_rel": {
                            "x": 1.0,
                            "y": 1.0
                        },
                        "bounds": {
                            "x": 0.0,
                            "y": 0.0
                        },
                        "bounds_rel": {
                            "x": 0.0,
                            "y": 0.0
                        },
                        "scale_filter": "disable",
                        "blend_method": "default",
                        "blend_type": "normal",
                        "show_transition": {
                            "duration": 0
                        },
                        "hide_transition": {
                            "duration": 0
                        },
                        "private_settings": {}
                    },
                    {
                        "name": "name_3",
                        "source_uuid": "b8720018-af98-4a82-8f2f-51c8df17dbee",
                        "visible": true,
                        "locked": true,
                        "rot": 0.0,
                        "scale_ref": {
                            "x": 1920.0,
                            "y": 1080.0
                        },
                        "align": 5,
                        "bounds_type": 0,
                        "bounds_align": 0,
                        "bounds_crop": false,
                        "crop_left": 0,
                        "crop_top": 0,
                        "crop_right": 0,
                        "crop_bottom": 0,
                        "id": 15,
                        "group_item_backup": false,
                        "pos": {
                            "x": 480.0,
                            "y": 360.0
                        },
                        "pos_rel": {
                            "x": -0.8888888955116272,
                            "y": -0.3333333730697632
                        },
                        "scale": {
                            "x": 1.0,
                            "y": 1.0
                        },
                        "scale_rel": {
                            "x": 1.0,
                            "y": 1.0
                        },
                        "bounds": {
                            "x": 0.0,
                            "y": 0.0
                        },
                        "bounds_rel": {
                            "x": 0.0,
                            "y": 0.0
                        },
                        "scale_filter": "disable",
                        "blend_method": "default",
                        "blend_type": "normal",
                        "show_transition": {
                            "duration": 0
                        },
                        "hide_transition": {
                            "duration": 0
                        },
                        "private_settings": {}
                    },
                    {
                        "name": "name_4",
                        "source_uuid": "f3c0cdb8-5efe-4af2-977e-7d9fb47da6af",
                        "visible": true,
                        "locked": true,
                        "rot": 0.0,
                        "scale_ref": {
                            "x": 1920.0,
                            "y": 1080.0
                        },
                        "align": 5,
                        "bounds_type": 0,
                        "bounds_align": 0,
                        "bounds_crop": false,
                        "crop_left": 0,
                        "crop_top": 0,
                        "crop_right": 0,
                        "crop_bottom": 0,
                        "id": 16,
                        "group_item_backup": false,
                        "pos": {
                            "x": 1199.0,
                            "y": 0.0
                        },
                        "pos_rel": {
                            "x": 0.442592591047287,
                            "y": -1.0
                        },
                        "scale": {
                            "x": 1.0,
                            "y": 1.0
                        },
                        "scale_rel": {
                            "x": 1.0,
                            "y": 1.0
                        },
                        "bounds": {
                            "x": 0.0,
                            "y": 0.0
                        },
                        "bounds_rel": {
                            "x": 0.0,
                            "y": 0.0
                        },
                        "scale_filter": "disable",
                        "blend_method": "default",
                        "blend_type": "normal",
                        "show_transition": {
                            "duration": 0
                        },
                        "hide_transition": {
                            "duration": 0
                        },
                        "private_settings": {}
                    },
                    {
                        "name": "name_5",
                        "source_uuid": "dfbaf865-01cd-46cf-b05e-d24845c966dd",
                        "visible": true,
                        "locked": true,
                        "rot": 0.0,
                        "scale_ref": {
                            "x": 1920.0,
                            "y": 1080.0
                        },
                        "align": 5,
                        "bounds_type": 0,
                        "bounds_align": 0,
                        "bounds_crop": false,
                        "crop_left": 0,
                        "crop_top": 0,
                        "crop_right": 0,
                        "crop_bottom": 0,
                        "id": 17,
                        "group_item_backup": false,
                        "pos": {
                            "x": 960.0,
                            "y": 360.0
                        },
                        "pos_rel": {
                            "x": 0.0,
                            "y": -0.3333333730697632
                        },
                        "scale": {
                            "x": 1.0,
                            "y": 1.0
                        },
                        "scale_rel": {
                            "x": 1.0,
                            "y": 1.0
                        },
                        "bounds": {
                            "x": 0.0,
                            "y": 0.0
                        },
                        "bounds_rel": {
                            "x": 0.0,
                            "y": 0.0
                        },
                        "scale_filter": "disable",
                        "blend_method": "default",
                        "blend_type": "normal",
                        "show_transition": {
                            "duration": 0
                        },
                        "hide_transition": {
                            "duration": 0
                        },
                        "private_settings": {}
                    },
                    {
                        "name": "name_6",
                        "source_uuid": "91e149ba-607e-4b62-beb8-b2069b087047",
                        "visible": true,
                        "locked": true,
                        "rot": 0.0,
                        "scale_ref": {
                            "x": 1920.0,
                            "y": 1080.0
                        },
                        "align": 5,
                        "bounds_type": 0,
                        "bounds_align": 0,
                        "bounds_crop": false,
                        "crop_left": 0,
                        "crop_top": 0,
                        "crop_right": 0,
                        "crop_bottom": 0,
                        "id": 18,
                        "group_item_backup": false,
                        "pos": {
                            "x": 1440.0,
                            "y": 360.0
                        },
                        "pos_rel": {
                            "x": 0.8888888955116272,
                            "y": -0.3333333730697632
                        },
                        "scale": {
                            "x": 1.0,
                            "y": 1.0
                        },
                        "scale_rel": {
                            "x": 1.0,
                            "y": 1.0
                        },
                        "bounds": {
                            "x": 0.0,
                            "y": 0.0
                        },
                        "bounds_rel": {
                            "x": 0.0,
                            "y": 0.0
                        },
                        "scale_filter": "disable",
                        "blend_method": "default",
                        "blend_type": "normal",
                        "show_transition": {
                            "duration": 0
                        },
                        "hide_transition": {
                            "duration": 0
                        },
                        "private_settings": {}
                    }
                ]
            },
            "mixers": 0,
            "sync": 0,
            "flags": 0,
            "volume": 1.0,
            "balance": 0.5,
            "enabled": true,
            "muted": false,
            "push-to-mute": false,
            "push-to-mute-delay": 0,
            "push-to-talk": false,
            "push-to-talk-delay": 0,
            "hotkeys": {
                "libobs.show_scene_item.13": [],
                "libobs.hide_scene_item.13": [],
                "libobs.show_scene_item.14": [],
                "libobs.hide_scene_item.14": [],
                "libobs.show_scene_item.15": [],
                "libobs.hide_scene_item.15": [],
                "libobs.show_scene_item.16": [],
                "libobs.hide_scene_item.16": [],
                "libobs.show_scene_item.17": [],
                "libobs.hide_scene_item.17": [],
                "libobs.show_scene_item.18": [],
                "libobs.hide_scene_item.18": []
            },
            "deinterlace_mode": 0,
            "deinterlace_field_order": 0,
            "monitoring_type": 0,
            "canvas_uuid": "6c69626f-6273-4c00-9d88-c5136d61696e",
            "private_settings": {}
        }
    ],
    "quick_transitions": [
        {
            "name": "Cut",
            "duration": 300,
            "hotkeys": [],
            "id": 10,
            "fade_to_black": false
        },
        {
            "name": "Fade",
            "duration": 300,
            "hotkeys": [],
            "id": 11,
            "fade_to_black": false
        },
        {
            "name": "Fade",
            "duration": 300,
            "hotkeys": [],
            "id": 12,
            "fade_to_black": true
        }
    ],
    "transitions": [
        {
            "name": "Luma Wipe",
            "id": "wipe_transition",
            "settings": {}
        }
    ],
    "saved_projectors": [],
    "canvases": [],
    "current_transition": "Luma Wipe",
    "transition_duration": 300,
    "preview_locked": false,
    "scaling_enabled": false,
    "scaling_level": -5,
    "scaling_off_x": 0.0,
    "scaling_off_y": 0.0,
    "virtual-camera": {
        "type2": 3
    },
    "modules": {
        "scripts-tool": [],
        "output-timer": {
            "streamTimerHours": 0,
            "streamTimerMinutes": 0,
            "streamTimerSeconds": 30,
            "recordTimerHours": 0,
            "recordTimerMinutes": 0,
            "recordTimerSeconds": 30,
            "autoStartStreamTimer": false,
            "autoStartRecordTimer": false,
            "pauseRecordTimer": true
        },
        "auto-scene-switcher": {
            "interval": 300,
            "non_matching_scene": "",
            "switch_if_not_matching": false,
            "active": false,
            "switches": []
        },
        "captions": {
            "source": "",
            "enabled": false,
            "lang_id": 1033,
            "provider": "mssapi"
        }
    },
    "resolution": {
        "x": 1920,
        "y": 1080
    },
    "version": 2,
    "sources": [
        {
            "prev_ver": 536870916,
            "name": "gameplay",
            "uuid": "7678dc5b-acd3-4c1f-85dc-60809a1a2e3e",
            "id": "scene",
            "versioned_id": "scene",
            "settings": {
                "id_counter": 19,
                "custom_size": false,
                "items": [
                    {
                        "name": "gameplay_overlay",
                        "source_uuid": "203d0615-6480-4a75-b74b-36c5fe5cb71d",
                        "visible": true,
                        "locked": true,
                        "rot": 0.0,
                        "scale_ref": {
                            "x": 1920.0,
                            "y": 1080.0
                        },
                        "align": 5,
                        "bounds_type": 0,
                        "bounds_align": 0,
                        "bounds_crop": false,
                        "crop_left": 0,
                        "crop_top": 0,
                        "crop_right": 0,
                        "crop_bottom": 0,
                        "id": 12,
                        "group_item_backup": false,
                        "pos": {
                            "x": 0.0,
                            "y": 0.0
                        },
                        "pos_rel": {
                            "x": -1.7777777910232544,
                            "y": -1.0
                        },
                        "scale": {
                            "x": 1.0,
                            "y": 1.0
                        },
                        "scale_rel": {
                            "x": 1.0,
                            "y": 1.0
                        },
                        "bounds": {
                            "x": 0.0,
                            "y": 0.0
                        },
                        "bounds_rel": {
                            "x": 0.0,
                            "y": 0.0
                        },
                        "scale_filter": "disable",
                        "blend_method": "default",
                        "blend_type": "normal",
                        "show_transition": {
                            "duration": 0
                        },
                        "hide_transition": {
                            "duration": 0
                        },
                        "private_settings": {}
                    },
                    {
                        "name": "osu_0",
                        "source_uuid": "d9a304d4-76f8-443b-b337-c078c9e2496c",
                        "visible": true,
                        "locked": true,
                        "rot": 0.0,
                        "scale_ref": {
                            "x": 1920.0,
                            "y": 1080.0
                        },
                        "align": 5,
                        "bounds_type": 0,
                        "bounds_align": 0,
                        "bounds_crop": false,
                        "crop_left": 0,
                        "crop_top": 0,
                        "crop_right": 0,
                        "crop_bottom": 0,
                        "id": 3,
                        "group_item_backup": true,
                        "pos": {
                            "x": 240.0,
                            "y": 196.0
                        },
                        "pos_rel": {
                            "x": -1.3333333730697632,
                            "y": -0.6370370388031006
                        },
                        "scale": {
                            "x": 1.0,
                            "y": 1.0
                        },
                        "scale_rel": {
                            "x": 1.0,
                            "y": 1.0
                        },
                        "bounds": {
                            "x": 0.0,
                            "y": 0.0
                        },
                        "bounds_rel": {
                            "x": 0.0,
                            "y": 0.0
                        },
                        "scale_filter": "disable",
                        "blend_method": "default",
                        "blend_type": "normal",
                        "show_transition": {
                            "duration": 0
                        },
                        "hide_transition": {
                            "duration": 0
                        },
                        "private_settings": {}
                    },
                    {
                        "name": "osu_1",
                        "source_uuid": "f1c4fdcf-52ee-450c-9054-b2edd7a7861f",
                        "visible": true,
                        "locked": true,
                        "rot": 0.0,
                        "scale_ref": {
                            "x": 1920.0,
                            "y": 1080.0
                        },
                        "align": 5,
                        "bounds_type": 0,
                        "bounds_align": 0,
                        "bounds_crop": false,
                        "crop_left": 0,
                        "crop_top": 0,
                        "crop_right": 0,
                        "crop_bottom": 0,
                        "id": 4,
                        "group_item_backup": true,
                        "pos": {
                            "x": 0.0,
                            "y": 556.0
                        },
                        "pos_rel": {
                            "x": -1.7777777910232544,
                            "y": 0.02962958812713623
                        },
                        "scale": {
                            "x": 1.0,
                            "y": 1.0
                        },
                        "scale_rel": {
                            "x": 1.0,
                            "y": 1.0
                        },
                        "bounds": {
                            "x": 0.0,
                            "y": 0.0
                        },
                        "bounds_rel": {
                            "x": 0.0,
                            "y": 0.0
                        },
                        "scale_filter": "disable",
                        "blend_method": "default",
                        "blend_type": "normal",
                        "show_transition": {
                            "duration": 0
                        },
                        "hide_transition": {
                            "duration": 0
                        },
                        "private_settings": {}
                    },
                    {
                        "name": "osu_2",
                        "source_uuid": "74814e97-60e8-4a64-a404-76626034266d",
                        "visible": true,
                        "locked": true,
                        "rot": 0.0,
                        "scale_ref": {
                            "x": 1920.0,
                            "y": 1080.0
                        },
                        "align": 5,
                        "bounds_type": 0,
                        "bounds_align": 0,
                        "bounds_crop": false,
                        "crop_left": 0,
                        "crop_top": 0,
                        "crop_right": 0,
                        "crop_bottom": 0,
                        "id": 5,
                        "group_item_backup": true,
                        "pos": {
                            "x": 480.0,
                            "y": 556.0
                        },
                        "pos_rel": {
                            "x": -0.8888888955116272,
                            "y": 0.02962958812713623
                        },
                        "scale": {
                            "x": 1.0,
                            "y": 1.0
                        },
                        "scale_rel": {
                            "x": 1.0,
                            "y": 1.0
                        },
                        "bounds": {
                            "x": 0.0,
                            "y": 0.0
                        },
                        "bounds_rel": {
                            "x": 0.0,
                            "y": 0.0
                        },
                        "scale_filter": "disable",
                        "blend_method": "default",
                        "blend_type": "normal",
                        "show_transition": {
                            "duration": 0
                        },
                        "hide_transition": {
                            "duration": 0
                        },
                        "private_settings": {}
                    },
                    {
                        "name": "osu_3",
                        "source_uuid": "4d7b2937-3850-468f-a270-c7175b8db295",
                        "visible": true,
                        "locked": true,
                        "rot": 0.0,
                        "scale_ref": {
                            "x": 1920.0,
                            "y": 1080.0
                        },
                        "align": 5,
                        "bounds_type": 0,
                        "bounds_align": 0,
                        "bounds_crop": false,
                        "crop_left": 0,
                        "crop_top": 0,
                        "crop_right": 0,
                        "crop_bottom": 0,
                        "id": 6,
                        "group_item_backup": true,
                        "pos": {
                            "x": 1199.0,
                            "y": 196.0
                        },
                        "pos_rel": {
                            "x": 0.442592591047287,
                            "y": -0.6370370388031006
                        },
                        "scale": {
                            "x": 1.0,
                            "y": 1.0
                        },
                        "scale_rel": {
                            "x": 1.0,
                            "y": 1.0
                        },
                        "bounds": {
                            "x": 0.0,
                            "y": 0.0
                        },
                        "bounds_rel": {
                            "x": 0.0,
                            "y": 0.0
                        },
                        "scale_filter": "disable",
                        "blend_method": "default",
                        "blend_type": "normal",
                        "show_transition": {
                            "duration": 0
                        },
                        "hide_transition": {
                            "duration": 0
                        },
                        "private_settings": {}
                    },
                    {
                        "name": "osu_4",
                        "source_uuid": "4c171870-5a0e-4aa6-b13b-7949cc213cff",
                        "visible": true,
                        "locked": true,
                        "rot": 0.0,
                        "scale_ref": {
                            "x": 1920.0,
                            "y": 1080.0
                        },
                        "align": 5,
                        "bounds_type": 0,
                        "bounds_align": 0,
                        "bounds_crop": false,
                        "crop_left": 0,
                        "crop_top": 0,
                        "crop_right": 0,
                        "crop_bottom": 0,
                        "id": 7,
                        "group_item_backup": true,
                        "pos": {
                            "x": 960.0,
                            "y": 556.0
                        },
                        "pos_rel": {
                            "x": 0.0,
                            "y": 0.02962958812713623
                        },
                        "scale": {
                            "x": 1.0,
                            "y": 1.0
                        },
                        "scale_rel": {
                            "x": 1.0,
                            "y": 1.0
                        },
                        "bounds": {
                            "x": 0.0,
                            "y": 0.0
                        },
                        "bounds_rel": {
                            "x": 0.0,
                            "y": 0.0
                        },
                        "scale_filter": "disable",
                        "blend_method": "default",
                        "blend_type": "normal",
                        "show_transition": {
                            "duration": 0
                        },
                        "hide_transition": {
                            "duration": 0
                        },
                        "private_settings": {}
                    },
                    {
                        "name": "osu_5",
                        "source_uuid": "3b912092-2f46-458d-9c51-c18c91d7996a",
                        "visible": true,
                        "locked": true,
                        "rot": 0.0,
                        "scale_ref": {
                            "x": 1920.0,
                            "y": 1080.0
                        },
                        "align": 5,
                        "bounds_type": 0,
                        "bounds_align": 0,
                        "bounds_crop": false,
                        "crop_left": 0,
                        "crop_top": 0,
                        "crop_right": 0,
                        "crop_bottom": 0,
                        "id": 8,
                        "group_item_backup": true,
                        "pos": {
                            "x": 1440.0,
                            "y": 556.0
                        },
                        "pos_rel": {
                            "x": 0.8888888955116272,
                            "y": 0.02962958812713623
                        },
                        "scale": {
                            "x": 1.0,
                            "y": 1.0
                        },
                        "scale_rel": {
                            "x": 1.0,
                            "y": 1.0
                        },
                        "bounds": {
                            "x": 0.0,
                            "y": 0.0
                        },
                        "bounds_rel": {
                            "x": 0.0,
                            "y": 0.0
                        },
                        "scale_filter": "disable",
                        "blend_method": "default",
                        "blend_type": "normal",
                        "show_transition": {
                            "duration": 0
                        },
                        "hide_transition": {
                            "duration": 0
                        },
                        "private_settings": {}
                    },
                    {
                        "name": "osu_clients",
                        "source_uuid": "91e24224-4a94-477c-9511-f8bed15ac9e7",
                        "visible": true,
                        "locked": true,
                        "rot": 0.0,
                        "scale_ref": {
                            "x": 1920.0,
                            "y": 1080.0
                        },
                        "align": 5,
                        "bounds_type": 0,
                        "bounds_align": 0,
                        "bounds_crop": false,
                        "crop_left": 0,
                        "crop_top": 0,
                        "crop_right": 0,
                        "crop_bottom": 0,
                        "id": 11,
                        "group_item_backup": false,
                        "pos": {
                            "x": 0.0,
                            "y": 196.0
                        },
                        "pos_rel": {
                            "x": -1.7777777910232544,
                            "y": -0.6370370388031006
                        },
                        "scale": {
                            "x": 1.0,
                            "y": 1.0
                        },
                        "scale_rel": {
                            "x": 1.0,
                            "y": 1.0
                        },
                        "bounds": {
                            "x": 0.0,
                            "y": 0.0
                        },
                        "bounds_rel": {
                            "x": 0.0,
                            "y": 0.0
                        },
                        "scale_filter": "disable",
                        "blend_method": "default",
                        "blend_type": "normal",
                        "show_transition": {
                            "duration": 0
                        },
                        "hide_transition": {
                            "duration": 0
                        },
                        "private_settings": {
                            "collapsed": false
                        }
                    },
                    {
                        "name": "name_1",
                        "source_uuid": "9ebf5713-15e7-4168-9571-5e563578ada7",
                        "visible": true,
                        "locked": true,
                        "rot": 0.0,
                        "scale_ref": {
                            "x": 1920.0,
                            "y": 1080.0
                        },
                        "align": 5,
                        "bounds_type": 0,
                        "bounds_align": 0,
                        "bounds_crop": false,
                        "crop_left": 0,
                        "crop_top": 0,
                        "crop_right": 0,
                        "crop_bottom": 0,
                        "id": 13,
                        "group_item_backup": true,
                        "pos": {
                            "x": 240.0,
                            "y": 196.0
                        },
                        "pos_rel": {
                            "x": -1.3333333730697632,
                            "y": -0.6370370388031006
                        },
                        "scale": {
                            "x": 1.0,
                            "y": 1.0
                        },
                        "scale_rel": {
                            "x": 1.0,
                            "y": 1.0
                        },
                        "bounds": {
                            "x": 0.0,
                            "y": 0.0
                        },
                        "bounds_rel": {
                            "x": 0.0,
                            "y": 0.0
                        },
                        "scale_filter": "disable",
                        "blend_method": "default",
                        "blend_type": "normal",
                        "show_transition": {
                            "duration": 0
                        },
                        "hide_transition": {
                            "duration": 0
                        },
                        "private_settings": {}
                    },
                    {
                        "name": "name_2",
                        "source_uuid": "c6b60609-e4d0-45ac-bdfb-3aca589e4be4",
                        "visible": true,
                        "locked": true,
                        "rot": 0.0,
                        "scale_ref": {
                            "x": 1920.0,
                            "y": 1080.0
                        },
                        "align": 5,
                        "bounds_type": 0,
                        "bounds_align": 0,
                        "bounds_crop": false,
                        "crop_left": 0,
                        "crop_top": 0,
                        "crop_right": 0,
                        "crop_bottom": 0,
                        "id": 14,
                        "group_item_backup": true,
                        "pos": {
                            "x": 0.0,
                            "y": 556.0
                        },
                        "pos_rel": {
                            "x": -1.7777777910232544,
                            "y": 0.02962958812713623
                        },
                        "scale": {
                            "x": 1.0,
                            "y": 1.0
                        },
                        "scale_rel": {
                            "x": 1.0,
                            "y": 1.0
                        },
                        "bounds": {
                            "x": 0.0,
                            "y": 0.0
                        },
                        "bounds_rel": {
                            "x": 0.0,
                            "y": 0.0
                        },
                        "scale_filter": "disable",
                        "blend_method": "default",
                        "blend_type": "normal",
                        "show_transition": {
                            "duration": 0
                        },
                        "hide_transition": {
                            "duration": 0
                        },
                        "private_settings": {}
                    },
                    {
                        "name": "name_3",
                        "source_uuid": "b8720018-af98-4a82-8f2f-51c8df17dbee",
                        "visible": true,
                        "locked": true,
                        "rot": 0.0,
                        "scale_ref": {
                            "x": 1920.0,
                            "y": 1080.0
                        },
                        "align": 5,
                        "bounds_type": 0,
                        "bounds_align": 0,
                        "bounds_crop": false,
                        "crop_left": 0,
                        "crop_top": 0,
                        "crop_right": 0,
                        "crop_bottom": 0,
                        "id": 15,
                        "group_item_backup": true,
                        "pos": {
                            "x": 480.0,
                            "y": 556.0
                        },
                        "pos_rel": {
                            "x": -0.8888888955116272,
                            "y": 0.02962958812713623
                        },
                        "scale": {
                            "x": 1.0,
                            "y": 1.0
                        },
                        "scale_rel": {
                            "x": 1.0,
                            "y": 1.0
                        },
                        "bounds": {
                            "x": 0.0,
                            "y": 0.0
                        },
                        "bounds_rel": {
                            "x": 0.0,
                            "y": 0.0
                        },
                        "scale_filter": "disable",
                        "blend_method": "default",
                        "blend_type": "normal",
                        "show_transition": {
                            "duration": 0
                        },
                        "hide_transition": {
                            "duration": 0
                        },
                        "private_settings": {}
                    },
                    {
                        "name": "name_4",
                        "source_uuid": "f3c0cdb8-5efe-4af2-977e-7d9fb47da6af",
                        "visible": true,
                        "locked": true,
                        "rot": 0.0,
                        "scale_ref": {
                            "x": 1920.0,
                            "y": 1080.0
                        },
                        "align": 5,
                        "bounds_type": 0,
                        "bounds_align": 0,
                        "bounds_crop": false,
                        "crop_left": 0,
                        "crop_top": 0,
                        "crop_right": 0,
                        "crop_bottom": 0,
                        "id": 16,
                        "group_item_backup": true,
                        "pos": {
                            "x": 1199.0,
                            "y": 196.0
                        },
                        "pos_rel": {
                            "x": 0.442592591047287,
                            "y": -0.6370370388031006
                        },
                        "scale": {
                            "x": 1.0,
                            "y": 1.0
                        },
                        "scale_rel": {
                            "x": 1.0,
                            "y": 1.0
                        },
                        "bounds": {
                            "x": 0.0,
                            "y": 0.0
                        },
                        "bounds_rel": {
                            "x": 0.0,
                            "y": 0.0
                        },
                        "scale_filter": "disable",
                        "blend_method": "default",
                        "blend_type": "normal",
                        "show_transition": {
                            "duration": 0
                        },
                        "hide_transition": {
                            "duration": 0
                        },
                        "private_settings": {}
                    },
                    {
                        "name": "name_5",
                        "source_uuid": "dfbaf865-01cd-46cf-b05e-d24845c966dd",
                        "visible": true,
                        "locked": true,
                        "rot": 0.0,
                        "scale_ref": {
                            "x": 1920.0,
                            "y": 1080.0
                        },
                        "align": 5,
                        "bounds_type": 0,
                        "bounds_align": 0,
                        "bounds_crop": false,
                        "crop_left": 0,
                        "crop_top": 0,
                        "crop_right": 0,
                        "crop_bottom": 0,
                        "id": 17,
                        "group_item_backup": true,
                        "pos": {
                            "x": 960.0,
                            "y": 556.0
                        },
                        "pos_rel": {
                            "x": 0.0,
                            "y": 0.02962958812713623
                        },
                        "scale": {
                            "x": 1.0,
                            "y": 1.0
                        },
                        "scale_rel": {
                            "x": 1.0,
                            "y": 1.0
                        },
                        "bounds": {
                            "x": 0.0,
                            "y": 0.0
                        },
                        "bounds_rel": {
                            "x": 0.0,
                            "y": 0.0
                        },
                        "scale_filter": "disable",
                        "blend_method": "default",
                        "blend_type": "normal",
                        "show_transition": {
                            "duration": 0
                        },
                        "hide_transition": {
                            "duration": 0
                        },
                        "private_settings": {}
                    },
                    {
                        "name": "name_6",
                        "source_uuid": "91e149ba-607e-4b62-beb8-b2069b087047",
                        "visible": true,
                        "locked": true,
                        "rot": 0.0,
                        "scale_ref": {
                            "x": 1920.0,
                            "y": 1080.0
                        },
                        "align": 5,
                        "bounds_type": 0,
                        "bounds_align": 0,
                        "bounds_crop": false,
                        "crop_left": 0,
                        "crop_top": 0,
                        "crop_right": 0,
                        "crop_bottom": 0,
                        "id": 18,
                        "group_item_backup": true,
                        "pos": {
                            "x": 1440.0,
                            "y": 556.0
                        },
                        "pos_rel": {
                            "x": 0.8888888955116272,
                            "y": 0.02962958812713623
                        },
                        "scale": {
                            "x": 1.0,
                            "y": 1.0
                        },
                        "scale_rel": {
                            "x": 1.0,
                            "y": 1.0
                        },
                        "bounds": {
                            "x": 0.0,
                            "y": 0.0
                        },
                        "bounds_rel": {
                            "x": 0.0,
                            "y": 0.0
                        },
                        "scale_filter": "disable",
                        "blend_method": "default",
                        "blend_type": "normal",
                        "show_transition": {
                            "duration": 0
                        },
                        "hide_transition": {
                            "duration": 0
                        },
                        "private_settings": {}
                    },
                    {
                        "name": "names",
                        "source_uuid": "39f30a38-2a54-4b57-8416-a30346ccaa47",
                        "visible": true,
                        "locked": true,
                        "rot": 0.0,
                        "scale_ref": {
                            "x": 1920.0,
                            "y": 1080.0
                        },
                        "align": 5,
                        "bounds_type": 0,
                        "bounds_align": 0,
                        "bounds_crop": false,
                        "crop_left": 0,
                        "crop_top": 0,
                        "crop_right": 0,
                        "crop_bottom": 0,
                        "id": 19,
                        "group_item_backup": false,
                        "pos": {
                            "x": 0.0,
                            "y": 196.0
                        },
                        "pos_rel": {
                            "x": -1.7777777910232544,
                            "y": -0.6370370388031006
                        },
                        "scale": {
                            "x": 1.0,
                            "y": 1.0
                        },
                        "scale_rel": {
                            "x": 1.0,
                            "y": 1.0
                        },
                        "bounds": {
                            "x": 0.0,
                            "y": 0.0
                        },
                        "bounds_rel": {
                            "x": 0.0,
                            "y": 0.0
                        },
                        "scale_filter": "disable",
                        "blend_method": "default",
                        "blend_type": "normal",
                        "show_transition": {
                            "duration": 0
                        },
                        "hide_transition": {
                            "duration": 0
                        },
                        "private_settings": {}
                    }
                ]
            },
            "mixers": 0,
            "sync": 0,
            "flags": 0,
            "volume": 1.0,
            "balance": 0.5,
            "enabled": true,
            "muted": false,
            "push-to-mute": false,
            "push-to-mute-delay": 0,
            "push-to-talk": false,
            "push-to-talk-delay": 0,
            "hotkeys": {
                "OBSBasic.SelectScene": [],
                "libobs.show_scene_item.11": [],
                "libobs.hide_scene_item.11": [],
                "libobs.show_scene_item.12": [],
                "libobs.hide_scene_item.12": [],
                "libobs.show_scene_item.19": [],
                "libobs.hide_scene_item.19": []
            },
            "deinterlace_mode": 0,
            "deinterlace_field_order": 0,
            "monitoring_type": 0,
            "canvas_uuid": "6c69626f-6273-4c00-9d88-c5136d61696e",
            "private_settings": {}
        },
        {
            "prev_ver": 536870916,
            "name": "gameplay_overlay",
            "uuid": "203d0615-6480-4a75-b74b-36c5fe5cb71d",
            "id": "browser_source",
            "versioned_id": "browser_source",
            "settings": {
                "url": "http://127.0.0.1:24050/usc-stream-overlay/scenes/main/",
                "width": 1920,
                "height": 1080
            },
            "mixers": 255,
            "sync": 0,
            "flags": 0,
            "volume": 1.0,
            "balance": 0.5,
            "enabled": true,
            "muted": false,
            "push-to-mute": false,
            "push-to-mute-delay": 0,
            "push-to-talk": false,
            "push-to-talk-delay": 0,
            "hotkeys": {
                "libobs.mute": [],
                "libobs.unmute": [],
                "libobs.push-to-mute": [],
                "libobs.push-to-talk": [],
                "ObsBrowser.Refresh": []
            },
            "deinterlace_mode": 0,
            "deinterlace_field_order": 0,
            "monitoring_type": 0,
            "private_settings": {}
        },
        {
            "prev_ver": 536870916,
            "name": "mappool",
            "uuid": "b377be10-3fab-4f24-85c9-be8663866086",
            "id": "scene",
            "versioned_id": "scene",
            "settings": {
                "id_counter": 2,
                "custom_size": false,
                "items": [
                    {
                        "name": "mappool_background",
                        "source_uuid": "0c340aa3-15bd-44eb-986a-dd211a8a69f5",
                        "visible": true,
                        "locked": true,
                        "rot": 0.0,
                        "scale_ref": {
                            "x": 1920.0,
                            "y": 1080.0
                        },
                        "align": 5,
                        "bounds_type": 0,
                        "bounds_align": 0,
                        "bounds_crop": false,
                        "crop_left": 0,
                        "crop_top": 0,
                        "crop_right": 0,
                        "crop_bottom": 0,
                        "id": 2,
                        "group_item_backup": false,
                        "pos": {
                            "x": 0.0,
                            "y": 0.0
                        },
                        "pos_rel": {
                            "x": -1.7777777910232544,
                            "y": -1.0
                        },
                        "scale": {
                            "x": 1.0,
                            "y": 1.0
                        },
                        "scale_rel": {
                            "x": 1.0,
                            "y": 1.0
                        },
                        "bounds": {
                            "x": 0.0,
                            "y": 0.0
                        },
                        "bounds_rel": {
                            "x": 0.0,
                            "y": 0.0
                        },
                        "scale_filter": "disable",
                        "blend_method": "default",
                        "blend_type": "normal",
                        "show_transition": {
                            "duration": 0
                        },
                        "hide_transition": {
                            "duration": 0
                        },
                        "private_settings": {}
                    },
                    {
                        "name": "mappool_overlay",
                        "source_uuid": "cac9eb53-4715-4f0b-b24f-5fd0cce1f660",
                        "visible": true,
                        "locked": true,
                        "rot": 0.0,
                        "scale_ref": {
                            "x": 1920.0,
                            "y": 1080.0
                        },
                        "align": 5,
                        "bounds_type": 0,
                        "bounds_align": 0,
                        "bounds_crop": false,
                        "crop_left": 0,
                        "crop_top": 0,
                        "crop_right": 0,
                        "crop_bottom": 0,
                        "id": 1,
                        "group_item_backup": false,
                        "pos": {
                            "x": 0.0,
                            "y": 0.0
                        },
                        "pos_rel": {
                            "x": -1.7777777910232544,
                            "y": -1.0
                        },
                        "scale": {
                            "x": 1.0,
                            "y": 1.0
                        },
                        "scale_rel": {
                            "x": 1.0,
                            "y": 1.0
                        },
                        "bounds": {
                            "x": 0.0,
                            "y": 0.0
                        },
                        "bounds_rel": {
                            "x": 0.0,
                            "y": 0.0
                        },
                        "scale_filter": "disable",
                        "blend_method": "default",
                        "blend_type": "normal",
                        "show_transition": {
                            "duration": 0
                        },
                        "hide_transition": {
                            "duration": 0
                        },
                        "private_settings": {}
                    }
                ]
            },
            "mixers": 0,
            "sync": 0,
            "flags": 0,
            "volume": 1.0,
            "balance": 0.5,
            "enabled": true,
            "muted": false,
            "push-to-mute": false,
            "push-to-mute-delay": 0,
            "push-to-talk": false,
            "push-to-talk-delay": 0,
            "hotkeys": {
                "OBSBasic.SelectScene": [],
                "libobs.show_scene_item.1": [],
                "libobs.hide_scene_item.1": [],
                "libobs.show_scene_item.2": [],
                "libobs.hide_scene_item.2": []
            },
            "deinterlace_mode": 0,
            "deinterlace_field_order": 0,
            "monitoring_type": 0,
            "canvas_uuid": "6c69626f-6273-4c00-9d88-c5136d61696e",
            "private_settings": {}
        },
        {
            "prev_ver": 536870916,
            "name": "mappool_background",
            "uuid": "0c340aa3-15bd-44eb-986a-dd211a8a69f5",
            "id": "browser_source",
            "versioned_id": "browser_source",
            "settings": {
                "url": "http://127.0.0.1:24050/usc-stream-overlay/scenes/main/?mappool=true",
                "width": 1920,
                "height": 1080
            },
            "mixers": 255,
            "sync": 0,
            "flags": 0,
            "volume": 1.0,
            "balance": 0.5,
            "enabled": true,
            "muted": false,
            "push-to-mute": false,
            "push-to-mute-delay": 0,
            "push-to-talk": false,
            "push-to-talk-delay": 0,
            "hotkeys": {
                "libobs.mute": [],
                "libobs.unmute": [],
                "libobs.push-to-mute": [],
                "libobs.push-to-talk": [],
                "ObsBrowser.Refresh": []
            },
            "deinterlace_mode": 0,
            "deinterlace_field_order": 0,
            "monitoring_type": 0,
            "private_settings": {}
        },
        {
            "prev_ver": 536870916,
            "name": "mappool_overlay",
            "uuid": "cac9eb53-4715-4f0b-b24f-5fd0cce1f660",
            "id": "browser_source",
            "versioned_id": "browser_source",
            "settings": {
                "url": "http://127.0.0.1:24050/usc-stream-overlay/scenes/mappool/",
                "width": 2220,
                "height": 1080,
                "webpage_control_level": 4
            },
            "mixers": 255,
            "sync": 0,
            "flags": 0,
            "volume": 1.0,
            "balance": 0.5,
            "enabled": true,
            "muted": false,
            "push-to-mute": false,
            "push-to-mute-delay": 0,
            "push-to-talk": false,
            "push-to-talk-delay": 0,
            "hotkeys": {
                "libobs.mute": [],
                "libobs.unmute": [],
                "libobs.push-to-mute": [],
                "libobs.push-to-talk": [],
                "ObsBrowser.Refresh": []
            },
            "deinterlace_mode": 0,
            "deinterlace_field_order": 0,
            "monitoring_type": 0,
            "private_settings": {}
        },
        {
            "prev_ver": 536870916,
            "name": "name_1",
            "uuid": "9ebf5713-15e7-4168-9571-5e563578ada7",
            "id": "browser_source",
            "versioned_id": "browser_source",
            "settings": {
                "width": 480,
                "height": 40,
                "url": "http://127.0.0.1:24050/usc-stream-overlay/scenes/names/?id=1&fontSize=20&placeholder=Waiting...&debug=false"
            },
            "mixers": 255,
            "sync": 0,
            "flags": 0,
            "volume": 1.0,
            "balance": 0.5,
            "enabled": true,
            "muted": false,
            "push-to-mute": false,
            "push-to-mute-delay": 0,
            "push-to-talk": false,
            "push-to-talk-delay": 0,
            "hotkeys": {
                "libobs.mute": [],
                "libobs.unmute": [],
                "libobs.push-to-mute": [],
                "libobs.push-to-talk": [],
                "ObsBrowser.Refresh": []
            },
            "deinterlace_mode": 0,
            "deinterlace_field_order": 0,
            "monitoring_type": 0,
            "private_settings": {}
        },
        {
            "prev_ver": 536870916,
            "name": "name_2",
            "uuid": "c6b60609-e4d0-45ac-bdfb-3aca589e4be4",
            "id": "browser_source",
            "versioned_id": "browser_source",
            "settings": {
                "url": "http://127.0.0.1:24050/usc-stream-overlay/scenes/names/?id=2&fontSize=20&placeholder=Waiting...&debug=false",
                "width": 480,
                "height": 40
            },
            "mixers": 255,
            "sync": 0,
            "flags": 0,
            "volume": 1.0,
            "balance": 0.5,
            "enabled": true,
            "muted": false,
            "push-to-mute": false,
            "push-to-mute-delay": 0,
            "push-to-talk": false,
            "push-to-talk-delay": 0,
            "hotkeys": {
                "libobs.mute": [],
                "libobs.unmute": [],
                "libobs.push-to-mute": [],
                "libobs.push-to-talk": [],
                "ObsBrowser.Refresh": []
            },
            "deinterlace_mode": 0,
            "deinterlace_field_order": 0,
            "monitoring_type": 0,
            "private_settings": {}
        },
        {
            "prev_ver": 536870916,
            "name": "name_3",
            "uuid": "b8720018-af98-4a82-8f2f-51c8df17dbee",
            "id": "browser_source",
            "versioned_id": "browser_source",
            "settings": {
                "url": "http://127.0.0.1:24050/usc-stream-overlay/scenes/names/?id=3&fontSize=20&placeholder=Waiting...&debug=false",
                "width": 480,
                "height": 40
            },
            "mixers": 255,
            "sync": 0,
            "flags": 0,
            "volume": 1.0,
            "balance": 0.5,
            "enabled": true,
            "muted": false,
            "push-to-mute": false,
            "push-to-mute-delay": 0,
            "push-to-talk": false,
            "push-to-talk-delay": 0,
            "hotkeys": {
                "libobs.mute": [],
                "libobs.unmute": [],
                "libobs.push-to-mute": [],
                "libobs.push-to-talk": [],
                "ObsBrowser.Refresh": []
            },
            "deinterlace_mode": 0,
            "deinterlace_field_order": 0,
            "monitoring_type": 0,
            "private_settings": {}
        },
        {
            "prev_ver": 536870916,
            "name": "name_4",
            "uuid": "f3c0cdb8-5efe-4af2-977e-7d9fb47da6af",
            "id": "browser_source",
            "versioned_id": "browser_source",
            "settings": {
                "url": "http://127.0.0.1:24050/usc-stream-overlay/scenes/names/?id=4&fontSize=20&placeholder=Waiting...&debug=false",
                "width": 480,
                "height": 40
            },
            "mixers": 255,
            "sync": 0,
            "flags": 0,
            "volume": 1.0,
            "balance": 0.5,
            "enabled": true,
            "muted": false,
            "push-to-mute": false,
            "push-to-mute-delay": 0,
            "push-to-talk": false,
            "push-to-talk-delay": 0,
            "hotkeys": {
                "libobs.mute": [],
                "libobs.unmute": [],
                "libobs.push-to-mute": [],
                "libobs.push-to-talk": [],
                "ObsBrowser.Refresh": []
            },
            "deinterlace_mode": 0,
            "deinterlace_field_order": 0,
            "monitoring_type": 0,
            "private_settings": {}
        },
        {
            "prev_ver": 536870916,
            "name": "name_5",
            "uuid": "dfbaf865-01cd-46cf-b05e-d24845c966dd",
            "id": "browser_source",
            "versioned_id": "browser_source",
            "settings": {
                "url": "http://127.0.0.1:24050/usc-stream-overlay/scenes/names/?id=5&fontSize=20&placeholder=Waiting...&debug=false",
                "width": 480,
                "height": 40
            },
            "mixers": 255,
            "sync": 0,
            "flags": 0,
            "volume": 1.0,
            "balance": 0.5,
            "enabled": true,
            "muted": false,
            "push-to-mute": false,
            "push-to-mute-delay": 0,
            "push-to-talk": false,
            "push-to-talk-delay": 0,
            "hotkeys": {
                "libobs.mute": [],
                "libobs.unmute": [],
                "libobs.push-to-mute": [],
                "libobs.push-to-talk": [],
                "ObsBrowser.Refresh": []
            },
            "deinterlace_mode": 0,
            "deinterlace_field_order": 0,
            "monitoring_type": 0,
            "private_settings": {}
        },
        {
            "prev_ver": 536870916,
            "name": "name_6",
            "uuid": "91e149ba-607e-4b62-beb8-b2069b087047",
            "id": "browser_source",
            "versioned_id": "browser_source",
            "settings": {
                "url": "http://127.0.0.1:24050/usc-stream-overlay/scenes/names/?id=6&fontSize=20&placeholder=Waiting...&debug=false",
                "width": 480,
                "height": 40
            },
            "mixers": 255,
            "sync": 0,
            "flags": 0,
            "volume": 1.0,
            "balance": 0.5,
            "enabled": true,
            "muted": false,
            "push-to-mute": false,
            "push-to-mute-delay": 0,
            "push-to-talk": false,
            "push-to-talk-delay": 0,
            "hotkeys": {
                "libobs.mute": [],
                "libobs.unmute": [],
                "libobs.push-to-mute": [],
                "libobs.push-to-talk": [],
                "ObsBrowser.Refresh": []
            },
            "deinterlace_mode": 0,
            "deinterlace_field_order": 0,
            "monitoring_type": 0,
            "private_settings": {}
        },
        {
            "prev_ver": 536870916,
            "name": "osu_0",
            "uuid": "d9a304d4-76f8-443b-b337-c078c9e2496c",
            "id": "window_capture",
            "versioned_id": "window_capture",
            "settings": {
                "window": " Tournament Client 0:WindowsForms10.Window.2b.app.0.1ca0192_r7_ad1:osu!.exe",
                "priority": 1,
                "cursor": false
            },
            "mixers": 255,
            "sync": 0,
            "flags": 0,
            "volume": 1.0,
            "balance": 0.5,
            "enabled": true,
            "muted": false,
            "push-to-mute": false,
            "push-to-mute-delay": 0,
            "push-to-talk": false,
            "push-to-talk-delay": 0,
            "hotkeys": {
                "libobs.mute": [],
                "libobs.unmute": [],
                "libobs.push-to-mute": [],
                "libobs.push-to-talk": []
            },
            "deinterlace_mode": 0,
            "deinterlace_field_order": 0,
            "monitoring_type": 0,
            "private_settings": {}
        },
        {
            "prev_ver": 536870916,
            "name": "osu_1",
            "uuid": "f1c4fdcf-52ee-450c-9054-b2edd7a7861f",
            "id": "window_capture",
            "versioned_id": "window_capture",
            "settings": {
                "window": " Tournament Client 1:WindowsForms10.Window.2b.app.0.1ca0192_r7_ad1:osu!.exe",
                "priority": 1,
                "cursor": false
            },
            "mixers": 255,
            "sync": 0,
            "flags": 0,
            "volume": 1.0,
            "balance": 0.5,
            "enabled": true,
            "muted": false,
            "push-to-mute": false,
            "push-to-mute-delay": 0,
            "push-to-talk": false,
            "push-to-talk-delay": 0,
            "hotkeys": {
                "libobs.mute": [],
                "libobs.unmute": [],
                "libobs.push-to-mute": [],
                "libobs.push-to-talk": []
            },
            "deinterlace_mode": 0,
            "deinterlace_field_order": 0,
            "monitoring_type": 0,
            "private_settings": {}
        },
        {
            "prev_ver": 536870916,
            "name": "osu_2",
            "uuid": "74814e97-60e8-4a64-a404-76626034266d",
            "id": "window_capture",
            "versioned_id": "window_capture",
            "settings": {
                "window": " Tournament Client 2:WindowsForms10.Window.2b.app.0.1ca0192_r7_ad1:osu!.exe",
                "priority": 1,
                "cursor": false
            },
            "mixers": 255,
            "sync": 0,
            "flags": 0,
            "volume": 1.0,
            "balance": 0.5,
            "enabled": true,
            "muted": false,
            "push-to-mute": false,
            "push-to-mute-delay": 0,
            "push-to-talk": false,
            "push-to-talk-delay": 0,
            "hotkeys": {
                "libobs.mute": [],
                "libobs.unmute": [],
                "libobs.push-to-mute": [],
                "libobs.push-to-talk": []
            },
            "deinterlace_mode": 0,
            "deinterlace_field_order": 0,
            "monitoring_type": 0,
            "private_settings": {}
        },
        {
            "prev_ver": 536870916,
            "name": "osu_3",
            "uuid": "4d7b2937-3850-468f-a270-c7175b8db295",
            "id": "window_capture",
            "versioned_id": "window_capture",
            "settings": {
                "window": " Tournament Client 3:WindowsForms10.Window.2b.app.0.1ca0192_r7_ad1:osu!.exe",
                "priority": 1,
                "cursor": false
            },
            "mixers": 255,
            "sync": 0,
            "flags": 0,
            "volume": 1.0,
            "balance": 0.5,
            "enabled": true,
            "muted": false,
            "push-to-mute": false,
            "push-to-mute-delay": 0,
            "push-to-talk": false,
            "push-to-talk-delay": 0,
            "hotkeys": {
                "libobs.mute": [],
                "libobs.unmute": [],
                "libobs.push-to-mute": [],
                "libobs.push-to-talk": []
            },
            "deinterlace_mode": 0,
            "deinterlace_field_order": 0,
            "monitoring_type": 0,
            "private_settings": {}
        },
        {
            "prev_ver": 536870916,
            "name": "osu_4",
            "uuid": "4c171870-5a0e-4aa6-b13b-7949cc213cff",
            "id": "window_capture",
            "versioned_id": "window_capture",
            "settings": {
                "window": " Tournament Client 4:WindowsForms10.Window.2b.app.0.1ca0192_r7_ad1:osu!.exe",
                "priority": 1,
                "cursor": false
            },
            "mixers": 255,
            "sync": 0,
            "flags": 0,
            "volume": 1.0,
            "balance": 0.5,
            "enabled": true,
            "muted": false,
            "push-to-mute": false,
            "push-to-mute-delay": 0,
            "push-to-talk": false,
            "push-to-talk-delay": 0,
            "hotkeys": {
                "libobs.mute": [],
                "libobs.unmute": [],
                "libobs.push-to-mute": [],
                "libobs.push-to-talk": []
            },
            "deinterlace_mode": 0,
            "deinterlace_field_order": 0,
            "monitoring_type": 0,
            "private_settings": {}
        },
        {
            "prev_ver": 536870916,
            "name": "osu_5",
            "uuid": "3b912092-2f46-458d-9c51-c18c91d7996a",
            "id": "window_capture",
            "versioned_id": "window_capture",
            "settings": {
                "window": " Tournament Client 5:WindowsForms10.Window.2b.app.0.1ca0192_r7_ad1:osu!.exe",
                "priority": 1,
                "cursor": false
            },
            "mixers": 255,
            "sync": 0,
            "flags": 0,
            "volume": 1.0,
            "balance": 0.5,
            "enabled": true,
            "muted": false,
            "push-to-mute": false,
            "push-to-mute-delay": 0,
            "push-to-talk": false,
            "push-to-talk-delay": 0,
            "hotkeys": {
                "libobs.mute": [],
                "libobs.unmute": [],
                "libobs.push-to-mute": [],
                "libobs.push-to-talk": []
            },
            "deinterlace_mode": 0,
            "deinterlace_field_order": 0,
            "monitoring_type": 0,
            "private_settings": {}
        }
    ]
}